{
  "15_400_15_1000": {
    "max memory": 1516785664,
    "#sessions": "16",
    "#transactions": "6001",
    "#events": "91000",
    "#constraints": "982558",
    "construct time": "34058ms",
    "prune time": "8992ms",
    "solver initializing time": "16328ms",
    "solve time": "13872ms",
    "accept": true,
    "total time": "73250ms"
  },
  "25_45_15_1000": {
    "max memory": 93843456,
    "#sessions": "26",
    "#transactions": "1126",
    "#events": "17875",
    "#constraints": "35590",
    "construct time": "160ms",
    "prune time": "171ms",
    "solver initializing time": "178ms",
    "solve time": "341ms",
    "accept": true,
    "total time": "850ms"
  },
  "15_45_15_1000": {
    "max memory": 57933824,
    "#sessions": "16",
    "#transactions": "676",
    "#events": "11125",
    "#constraints": "12755",
    "construct time": "30ms",
    "prune time": "38ms",
    "solver initializing time": "40ms",
    "solve time": "94ms",
    "accept": true,
    "total time": "202ms"
  },
  "15_45_15_1250": {
    "max memory": 54779904,
    "#sessions": "16",
    "#transactions": "676",
    "#events": "11375",
    "#constraints": "10629",
    "construct time": "24ms",
    "prune time": "24ms",
    "solver initializing time": "31ms",
    "solve time": "95ms",
    "accept": true,
    "total time": "174ms"
  },
  "15_15_15_1000": {
    "max memory": 38404096,
    "#sessions": "16",
    "#transactions": "226",
    "#events": "4347",
    "#constraints": "1492",
    "construct time": "3ms",
    "prune time": "2ms",
    "solver initializing time": "7ms",
    "solve time": "8ms",
    "accept": true,
    "total time": "20ms"
  },
  "15_45_15_750": {
    "max memory": 63922176,
    "#sessions": "16",
    "#transactions": "676",
    "#events": "10875",
    "#constraints": "16796",
    "construct time": "45ms",
    "prune time": "52ms",
    "solver initializing time": "55ms",
    "solve time": "113ms",
    "accept": true,
    "total time": "265ms"
  },
  "15_300_15_1000": {
    "max memory": 895098880,
    "#sessions": "16",
    "#transactions": "4501",
    "#events": "68500",
    "#constraints": "559672",
    "construct time": "14799ms",
    "prune time": "4790ms",
    "solver initializing time": "7825ms",
    "solve time": "8052ms",
    "accept": true,
    "total time": "35466ms"
  },
  "15_200_15_1000": {
    "max memory": 413310976,
    "#sessions": "16",
    "#transactions": "3001",
    "#events": "46000",
    "#constraints": "247367",
    "construct time": "3689ms",
    "prune time": "1795ms",
    "solver initializing time": "2463ms",
    "solve time": "2944ms",
    "accept": true,
    "total time": "10891ms"
  },
  "15_45_15_500": {
    "max memory": 74772480,
    "#sessions": "16",
    "#transactions": "676",
    "#events": "10625",
    "#constraints": "24835",
    "construct time": "86ms",
    "prune time": "87ms",
    "solver initializing time": "90ms",
    "solve time": "124ms",
    "accept": true,
    "total time": "387ms"
  },
  "15_45_5_1000": {
    "max memory": 40292352,
    "#sessions": "16",
    "#transactions": "676",
    "#events": "4341",
    "#constraints": "2143",
    "construct time": "4ms",
    "prune time": "3ms",
    "solver initializing time": "9ms",
    "solve time": "96ms",
    "accept": true,
    "total time": "112ms"
  },
  "15_45_20_1000": {
    "max memory": 72613888,
    "#sessions": "16",
    "#transactions": "676",
    "#events": "14500",
    "#constraints": "22020",
    "construct time": "82ms",
    "prune time": "91ms",
    "solver initializing time": "84ms",
    "solve time": "136ms",
    "accept": true,
    "total time": "393ms"
  },
  "10_45_15_1000": {
    "max memory": 46190592,
    "#sessions": "11",
    "#transactions": "451",
    "#events": "7749",
    "#constraints": "6236",
    "construct time": "13ms",
    "prune time": "11ms",
    "solver initializing time": "18ms",
    "solve time": "44ms",
    "accept": true,
    "total time": "86ms"
  },
  "15_30_15_1000": {
    "max memory": 46034944,
    "#sessions": "16",
    "#transactions": "451",
    "#events": "7748",
    "#constraints": "5863",
    "construct time": "12ms",
    "prune time": "12ms",
    "solver initializing time": "17ms",
    "solve time": "42ms",
    "accept": true,
    "total time": "83ms"
  },
  "15_45_15_1500": {
    "max memory": 52047872,
    "#sessions": "16",
    "#transactions": "676",
    "#events": "11624",
    "#constraints": "8786",
    "construct time": "20ms",
    "prune time": "19ms",
    "solver initializing time": "26ms",
    "solve time": "94ms",
    "accept": true,
    "total time": "159ms"
  },
  "15_60_15_1000": {
    "max memory": 74321920,
    "#sessions": "16",
    "#transactions": "901",
    "#events": "14500",
    "#constraints": "23616",
    "construct time": "82ms",
    "prune time": "103ms",
    "solver initializing time": "100ms",
    "solve time": "225ms",
    "accept": true,
    "total time": "510ms"
  },
  "5_45_15_1000": {
    "max memory": 38273024,
    "#sessions": "6",
    "#transactions": "226",
    "#events": "4343",
    "#constraints": "1507",
    "construct time": "3ms",
    "prune time": "2ms",
    "solver initializing time": "7ms",
    "solve time": "9ms",
    "accept": true,
    "total time": "21ms"
  },
  "15_600_15_1000": {
    "max memory": 3313451008,
    "#sessions": "16",
    "#transactions": "9001",
    "#events": "136000",
    "#constraints": "2214069",
    "construct time": "144369ms",
    "prune time": "22882ms",
    "solver initializing time": "53767ms",
    "solve time": "38476ms",
    "accept": true,
    "total time": "259494ms"
  },
  "15_75_15_1000": {
    "max memory": 94183424,
    "#sessions": "16",
    "#transactions": "1126",
    "#events": "17875",
    "#constraints": "35045",
    "construct time": "150ms",
    "prune time": "174ms",
    "solver initializing time": "180ms",
    "solve time": "366ms",
    "accept": true,
    "total time": "870ms"
  },
  "15_500_15_1000": {
    "max memory": 2363297792,
    "#sessions": "16",
    "#transactions": "7501",
    "#events": "113500",
    "#constraints": "1559468",
    "construct time": "89676ms",
    "prune time": "15331ms",
    "solver initializing time": "36452ms",
    "solve time": "25732ms",
    "accept": true,
    "total time": "167191ms"
  },
  "20_45_15_1000": {
    "max memory": 74432512,
    "#sessions": "21",
    "#transactions": "901",
    "#events": "14500",
    "#constraints": "22742",
    "construct time": "79ms",
    "prune time": "82ms",
    "solver initializing time": "99ms",
    "solve time": "198ms",
    "accept": true,
    "total time": "458ms"
  },
  "15_700_15_1000": {
    "max memory": 4376461312,
    "#sessions": "16",
    "#transactions": "10501",
    "#events": "158500",
    "#constraints": "3015027",
    "construct time": "187503ms",
    "prune time": "27872ms",
    "solver initializing time": "68395ms",
    "solve time": "48950ms",
    "accept": true,
    "total time": "332720ms"
  },
  "15_100_15_1000": {
    "max memory": 134430720,
    "#sessions": "16",
    "#transactions": "1501",
    "#events": "23500",
    "#constraints": "62430",
    "construct time": "390ms",
    "prune time": "357ms",
    "solver initializing time": "413ms",
    "solve time": "664ms",
    "accept": true,
    "total time": "1824ms"
  },
  "15_45_25_1000": {
    "max memory": 88453120,
    "#sessions": "16",
    "#transactions": "676",
    "#events": "17875",
    "#constraints": "33152",
    "construct time": "179ms",
    "prune time": "145ms",
    "solver initializing time": "185ms",
    "solve time": "157ms",
    "accept": true,
    "total time": "666ms"
  },
  "15_45_10_1000": {
    "max memory": 47509504,
    "#sessions": "16",
    "#transactions": "676",
    "#events": "7750",
    "#constraints": "6337",
    "construct time": "14ms",
    "prune time": "18ms",
    "solver initializing time": "26ms",
    "solve time": "93ms",
    "accept": true,
    "total time": "151ms"
  }
}