{
  "20_200_8_5000_0.5_r_1.5_100": {
    "max memory": 348131328,
    "#sessions": "21",
    "#transactions": "4001",
    "#events": "36929",
    "#constraints": "77024",
    "construct time": "295ms",
    "prune time": "631ms",
    "solver initializing time": "51ms",
    "solve time": "6584ms",
    "accept": true,
    "total time": "7561ms"
  },
  "20_300_8_5000_0.5_r_1.5_100": {
    "max memory": 600813568,
    "#sessions": "21",
    "#transactions": "6001",
    "#events": "52988",
    "#constraints": "163887",
    "construct time": "764ms",
    "prune time": "1753ms",
    "solver initializing time": "118ms",
    "solve time": "18792ms",
    "accept": true,
    "total time": "21427ms"
  },
  "20_400_8_5000_0.5_r_1.5_100": {
    "max memory": 874246144,
    "#sessions": "21",
    "#transactions": "8001",
    "#events": "68998",
    "#constraints": "272142",
    "construct time": "1703ms",
    "prune time": "3635ms",
    "solver initializing time": "204ms",
    "solve time": "42225ms",
    "accept": true,
    "total time": "47767ms"
  },
  "20_100_8_5000_0.5_r_1.5_100": {
    "max memory": 156536832,
    "#sessions": "21",
    "#transactions": "2001",
    "#events": "20482",
    "#constraints": "24497",
    "construct time": "49ms",
    "prune time": "142ms",
    "solver initializing time": "11ms",
    "solve time": "1182ms",
    "accept": true,
    "total time": "1384ms"
  },
  "20_500_8_5000_0.5_r_1.5_100": {
    "max memory": 1217376256,
    "#sessions": "21",
    "#transactions": "10001",
    "#events": "85000",
    "#constraints": "420881",
    "construct time": "2735ms",
    "prune time": "5280ms",
    "solver initializing time": "326ms",
    "solve time": "71699ms",
    "accept": true,
    "total time": "80040ms"
  }
}